datascience/__init__.py
datascience/download.py
datascience/ffmpeg.py
datascience/image.py
datascience/opencv.py
datascience/time.py
datascience/video.py
datascience/visualization.py
datascience_cjwcommuny-0.0.3.dist-info/LICENSE
datascience_cjwcommuny-0.0.3.dist-info/METADATA
datascience_cjwcommuny-0.0.3.dist-info/WHEEL
datascience_cjwcommuny-0.0.3.dist-info/top_level.txt
datascience_cjwcommuny-0.0.3.dist-info/RECORD
