Metadata-Version: 2.1
Name: datascience-cjwcommuny
Version: 0.0.3
Summary: datascience toolkit
Home-page: https://github.com/cjwcommuny/datascience
Author: cjwcommuny
Author-email: cjwcommuny@outlook.com
License: UNKNOWN
Platform: UNKNOWN
Classifier: Programming Language :: Python :: 3
Classifier: License :: OSI Approved :: MIT License
Classifier: Operating System :: OS Independent
Requires-Python: >=3.6
